sdk_cloud_dfe/Averbacao.py
sdk_cloud_dfe/Base.py
sdk_cloud_dfe/Certificado.py
sdk_cloud_dfe/Cliente.py
sdk_cloud_dfe/Cte.py
sdk_cloud_dfe/Cteos.py
sdk_cloud_dfe/Dfe.py
sdk_cloud_dfe/Emitente.py
sdk_cloud_dfe/Gnre.py
sdk_cloud_dfe/Mdfe.py
sdk_cloud_dfe/Nfce.py
sdk_cloud_dfe/Nfcom.py
sdk_cloud_dfe/Nfe.py
sdk_cloud_dfe/Nfse.py
sdk_cloud_dfe/RequestAPI.py
sdk_cloud_dfe/Services.py
sdk_cloud_dfe/Softhouse.py
sdk_cloud_dfe/Util.py
sdk_cloud_dfe/Webhook.py
sdk_cloud_dfe/__init__.py
sdk_cloud_dfe-1.1.2.dist-info/METADATA
sdk_cloud_dfe-1.1.2.dist-info/WHEEL
sdk_cloud_dfe-1.1.2.dist-info/top_level.txt
sdk_cloud_dfe-1.1.2.dist-info/RECORD
