Metadata-Version: 2.1
Name: sdk-cloud-dfe
Version: 1.1.2
Summary: SDK para comunicar com API Integra Notas.
Home-page: 
Author: Integra Notas
Author-email: comercial@cloud-dfe.com.br
Classifier: Programming Language :: Python :: 3
Classifier: License :: OSI Approved :: GNU Lesser General Public License v3 or later (LGPLv3+)
Classifier: License :: OSI Approved :: GNU General Public License v3 or later (GPLv3+)
Classifier: License :: OSI Approved :: MIT License
Classifier: Operating System :: OS Independent
Requires-Python: >=3.6
Requires-Dist: requests
Requires-Dist: pycryptodome
